ethbotutils/__init__.py
ethbotutils/bot_methods.py
ethbotutils/bot_util.py
ethbotutils-2.0.2.dist-info/METADATA
ethbotutils-2.0.2.dist-info/WHEEL
ethbotutils-2.0.2.dist-info/top_level.txt
ethbotutils-2.0.2.dist-info/RECORD
