Metadata-Version: 2.1
Name: ethbotutils
Version: 2.0.2
Summary: UNKNOWN
Home-page: UNKNOWN
Author: Alberto Pirillo
License: UNKNOWN
Platform: UNKNOWN
Requires-Python: >=3.6
Requires-Dist: requests (~=2.25.1)
Requires-Dist: PyYAML (~=5.4.1)
